booking_site_generator-0.1.0.dist-info/licenses/LICENSE
shablonizator/__init__.py
shablonizator/generator.py
shablonizator/site_templates/booking/admin.html
shablonizator/site_templates/booking/index.html
shablonizator/site_templates/booking/login.html
shablonizator/site_templates/booking/new-request.html
shablonizator/site_templates/booking/profile.html
shablonizator/site_templates/booking/registration.html
shablonizator/site_templates/booking/requests.html
shablonizator/site_templates/booking/css/Index.css
shablonizator/site_templates/booking/css/admin.css
shablonizator/site_templates/booking/css/styles.css
shablonizator/site_templates/booking/js/admin.js
shablonizator/site_templates/booking/js/auth.js
shablonizator/site_templates/booking/js/index.js
shablonizator/site_templates/booking/js/login.js
shablonizator/site_templates/booking/js/new-request.js
shablonizator/site_templates/booking/js/profile.js
shablonizator/site_templates/booking/js/registration.js
shablonizator/site_templates/booking/js/requests.js
booking_site_generator-0.1.0.dist-info/METADATA
booking_site_generator-0.1.0.dist-info/WHEEL
booking_site_generator-0.1.0.dist-info/entry_points.txt
booking_site_generator-0.1.0.dist-info/top_level.txt
booking_site_generator-0.1.0.dist-info/RECORD
