Metadata-Version: 2.4
Name: booking-site-generator
Version: 0.1.0
Summary: Генератор сайта для системы бронирования
Home-page: https://github.com/Y3ppi3/booking-site-generator
Author: katarymba
Author-email: email@example.com
Keywords: site generator booking website template
Classifier: Development Status :: 3 - Alpha
Classifier: Intended Audience :: Developers
Classifier: License :: OSI Approved :: MIT License
Classifier: Programming Language :: Python :: 3
Classifier: Programming Language :: Python :: 3.7
Classifier: Programming Language :: Python :: 3.8
Classifier: Programming Language :: Python :: 3.9
Requires-Python: >=3.7
License-File: LICENSE
Requires-Dist: setuptools>=45.0.0
Requires-Dist: wheel>=0.34.2
Dynamic: author
Dynamic: author-email
Dynamic: classifier
Dynamic: description
Dynamic: description-content-type
Dynamic: home-page
Dynamic: keywords
Dynamic: license-file
Dynamic: requires-dist
Dynamic: requires-python
Dynamic: summary
